zlibsanitizer.py
zlibsanitizer-1.2.dist-info/METADATA
zlibsanitizer-1.2.dist-info/WHEEL
zlibsanitizer-1.2.dist-info/RECORD
